{"__symbolic":"module","version":4,"metadata":{"HeadersLightingDirective":{"__symbolic":"class","decorators":[{"__symbolic":"call","expression":{"__symbolic":"reference","module":"@angular/core","name":"Directive","line":2,"character":1},"arguments":[{"selector":"[headersLighting]"}]}],"members":{"__ctor__":[{"__symbolic":"constructor","parameters":[{"__symbolic":"reference","module":"@angular/core","name":"ElementRef","line":10,"character":34}]}],"onMouseOver":[{"__symbolic":"method"}],"onMouseOut":[{"__symbolic":"method"}],"ngAfterViewInit":[{"__symbolic":"method"}],"ngAfterViewChecked":[{"__symbolic":"method"}],"deployListeners":[{"__symbolic":"method"}],"initListeners":[{"__symbolic":"method"}],"destroyListeners":[{"__symbolic":"method"}],"ngOnDestroy":[{"__symbolic":"method"}]}},"HeadersLightingModule":{"__symbolic":"class","decorators":[{"__symbolic":"call","expression":{"__symbolic":"reference","module":"@angular/core","name":"NgModule","line":4,"character":1},"arguments":[{"declarations":[{"__symbolic":"reference","name":"HeadersLightingDirective"}],"exports":[{"__symbolic":"reference","name":"HeadersLightingDirective"}],"imports":[],"providers":[]}]}],"members":{}}},"origins":{"HeadersLightingDirective":"./src/modules/headers-lighting.directive","HeadersLightingModule":"./src/modules/headers-lighting"},"importAs":"headers-lighting"}